utf/UnicodeData.txt
utf/__init__.py
utf/__main__.py
utf/emoji-en-US.json
utf/generate_db.py
utf/utf.tcss
utf_cli-0.3.3.dist-info/METADATA
utf_cli-0.3.3.dist-info/WHEEL
utf_cli-0.3.3.dist-info/entry_points.txt
utf_cli-0.3.3.dist-info/licenses/LICENSE.txt
utf_cli-0.3.3.dist-info/RECORD
