Metadata-Version: 2.3
Name: utf-cli
Version: 0.3.3
Project-URL: Documentation, https://github.com/treyhunner/utf-cli#readme
Project-URL: Issues, https://github.com/treyhunner/utf-cli/issues
Project-URL: Source, https://github.com/treyhunner/utf-cli
Author: Trey Hunner
License-Expression: MIT
License-File: LICENSE.txt
Classifier: Development Status :: 1 - Planning
Classifier: Programming Language :: Python
Classifier: Programming Language :: Python :: 3.8
Classifier: Programming Language :: Python :: 3.9
Classifier: Programming Language :: Python :: 3.10
Classifier: Programming Language :: Python :: 3.11
Classifier: Programming Language :: Python :: 3.12
Classifier: Programming Language :: Python :: Implementation :: CPython
Classifier: Programming Language :: Python :: Implementation :: PyPy
Requires-Python: >=3.8
Requires-Dist: darkdetect
Requires-Dist: platformdirs
Requires-Dist: pyperclip
Requires-Dist: textual
